pyseq.py
pyseq-0.5.1.data/scripts/lss
pyseq-0.5.1.dist-info/AUTHORS
pyseq-0.5.1.dist-info/LICENSE
pyseq-0.5.1.dist-info/METADATA
pyseq-0.5.1.dist-info/WHEEL
pyseq-0.5.1.dist-info/top_level.txt
pyseq-0.5.1.dist-info/RECORD
