Metadata-Version: 2.1
Name: pyseq
Version: 0.5.1
Summary: Compressed Sequence Python Module
Home-page: http://github.com/rsgalloway/pyseq
Author: Ryan Galloway
Author-email: ryan@rsgalloway.com
License: UNKNOWN
Platform: UNKNOWN
